iptcinfo3.py
iptcinfo3-2.2.0.dist-info/METADATA
iptcinfo3-2.2.0.dist-info/WHEEL
iptcinfo3-2.2.0.dist-info/RECORD
