Metadata-Version: 2.4
Name: IPTCInfo3
Version: 2.2.0
Summary: Extract and modify IPTC metadata from JPEG images
Project-URL: Homepage, https://github.com/jamesacampbell/iptcinfo3
Project-URL: Repository, https://github.com/jamesacampbell/iptcinfo3
Project-URL: Issues, https://github.com/jamesacampbell/iptcinfo3/issues
Author-email: Tamas Gulacsi <gthomas@fw.hu>
Maintainer-email: James Campbell <jc@normail.co>
License: Artistic-1.0 OR GPL-1.0-or-later
Keywords: exif,iptc,jpeg,metadata,photography
Classifier: Development Status :: 4 - Beta
Classifier: Intended Audience :: Developers
Classifier: License :: OSI Approved :: Artistic License
Classifier: License :: OSI Approved :: GNU General Public License (GPL)
Classifier: Programming Language :: Python
Classifier: Programming Language :: Python :: 3
Classifier: Programming Language :: Python :: 3.8
Classifier: Programming Language :: Python :: 3.9
Classifier: Programming Language :: Python :: 3.10
Classifier: Programming Language :: Python :: 3.11
Classifier: Programming Language :: Python :: 3.12
Classifier: Programming Language :: Python :: 3.13
Classifier: Topic :: Multimedia :: Graphics
Classifier: Topic :: Utilities
Requires-Python: >=3.8
Provides-Extra: dev
Requires-Dist: pytest-cov>=4.0; extra == 'dev'
Requires-Dist: pytest-watch>=4.2; extra == 'dev'
Requires-Dist: pytest>=7.0; extra == 'dev'
